ttkbootstrap_icons_gmi/__init__.py
ttkbootstrap_icons_gmi/glyphmap-baseline.json
ttkbootstrap_icons_gmi/glyphmap-outlined.json
ttkbootstrap_icons_gmi/glyphmap-round.json
ttkbootstrap_icons_gmi/glyphmap-sharp.json
ttkbootstrap_icons_gmi/glyphmap.json
ttkbootstrap_icons_gmi/icon.py
ttkbootstrap_icons_gmi/provider.py
ttkbootstrap_icons_gmi/LICENSES/Apache-2.0.txt
ttkbootstrap_icons_gmi/fonts/MaterialIcons-Regular.ttf
ttkbootstrap_icons_gmi/fonts/MaterialIconsOutlined-Regular.otf
ttkbootstrap_icons_gmi/fonts/MaterialIconsRound-Regular.otf
ttkbootstrap_icons_gmi/fonts/MaterialIconsSharp-Regular.otf
ttkbootstrap_icons_gmi/tools/__init__.py
ttkbootstrap_icons_gmi/tools/generate_assets.py
ttkbootstrap_icons_gmi-1.0.1.dist-info/METADATA
ttkbootstrap_icons_gmi-1.0.1.dist-info/WHEEL
ttkbootstrap_icons_gmi-1.0.1.dist-info/entry_points.txt
ttkbootstrap_icons_gmi-1.0.1.dist-info/top_level.txt
ttkbootstrap_icons_gmi-1.0.1.dist-info/RECORD
