Metadata-Version: 2.4
Name: ttkbootstrap-icons-gmi
Version: 1.0.1
Summary: Google Material Icons (baseline/outlined/round/sharp/twotone) provider for ttkbootstrap-icons
Author: Israel Dryer
License: MIT
Project-URL: Homepage, https://github.com/israel-dryer/ttkbootstrap-icons
Requires-Python: >=3.10
Requires-Dist: Pillow>=9.1
Requires-Dist: ttkbootstrap-icons>=3.0.0
